LICENSE
MANIFEST.in
README.md
setup.py
fpvad/ERI_VAD.pth
fpvad/VAD.py
fpvad/__init__.py
fpvad/pyannote_v2.json
fpvad.egg-info/PKG-INFO
fpvad.egg-info/SOURCES.txt
fpvad.egg-info/dependency_links.txt
fpvad.egg-info/requires.txt
fpvad.egg-info/top_level.txt