Metadata-Version: 2.1
Name: fpvad
Version: 0.0.16
Summary: Detects voice activity in audio files
Author: FanPars
License-File: LICENSE
Requires-Dist: asteroid-filterbanks==0.4.0
